draughts/PDN.py
draughts/__init__.py
draughts/ballots.py
draughts/convert.py
draughts/engine.py
draughts/svg.py
draughts/tournament.py
draughts/ballot_files/11_english.json
draughts/ballot_files/11_italian.json
draughts/ballot_files/150russian_and_brazilian.json
draughts/ballot_files/2move_english.json
draughts/ballot_files/3move_english.json
draughts/ballot_files/4move_english.json
draughts/ballot_files/5move_english.json
draughts/ballot_files/__init__.py
draughts/ballot_files/brazilian.json
draughts/ballot_files/russian.json
draughts/core/__init__.py
draughts/core/board.py
draughts/core/board_initializer.py
draughts/core/board_searcher.py
draughts/core/game.py
draughts/core/move.py
draughts/core/piece.py
draughts/core/variant.py
draughts/engines/__init__.py
draughts/engines/checkerboard.py
draughts/engines/dxp.py
draughts/engines/hub.py
draughts/engines/checkerboard_extra/__init__.py
draughts/engines/checkerboard_extra/engine_64.py
draughts/engines/checkerboard_extra/engine_client.py
draughts/engines/checkerboard_extra/engine_server.py
draughts/engines/checkerboard_extra/get_checker_board.py
draughts/engines/dxp_communication/__init__.py
draughts/engines/dxp_communication/dxp_classes.py
draughts/engines/dxp_communication/dxp_communication.py
pydraughts-0.6.7.dist-info/ImparaAI checkers LICENSE
pydraughts-0.6.7.dist-info/LICENSE
pydraughts-0.6.7.dist-info/METADATA
pydraughts-0.6.7.dist-info/WHEEL
pydraughts-0.6.7.dist-info/akalverboer DXC100_draughts_client LICENSE
pydraughts-0.6.7.dist-info/fishnet LICENSE.txt
pydraughts-0.6.7.dist-info/top_level.txt
pydraughts-0.6.7.dist-info/RECORD
