Metadata-Version: 2.2
Name: pydraughts
Version: 0.6.7
Summary: A draughts library for Python with move generation, SVG visualizations, PDN reading and writing, engine communication and balloted openings
Home-page: https://github.com/AttackingOrDefending/pydraughts
Author: Ioannis Pantidis
Project-URL: Bug Tracker, https://github.com/AttackingOrDefending/pydraughts/issues
Keywords: checkers,draughts,game,fen,pdn
Classifier: Intended Audience :: Developers
Classifier: Intended Audience :: Science/Research
Classifier: Programming Language :: Python :: 3
Classifier: License :: OSI Approved :: MIT License
Classifier: Operating System :: OS Independent
Classifier: Topic :: Games/Entertainment :: Board Games
Classifier: Topic :: Games/Entertainment :: Turn Based Strategy
Classifier: Topic :: Software Development :: Libraries :: Python Modules
Requires-Python: >=3.8
License-File: LICENSE
License-File: other_licenses\ImparaAI checkers LICENSE
License-File: other_licenses\akalverboer DXC100_draughts_client LICENSE
License-File: other_licenses\fishnet LICENSE.txt
Requires-Dist: msl-loadlib==0.10.0
